llmconf/__init__.py
llmconf/confs/__init__.py
llmconf/confs/base_conf.py
llmconf/confs/openai_conf.py
llmconf/confs/transf_conf.py
llmconf/main.py
llmconf/simple_llm.py
llmconf-0.5.0.dist-info/LICENSE
llmconf-0.5.0.dist-info/METADATA
llmconf-0.5.0.dist-info/WHEEL
llmconf-0.5.0.dist-info/RECORD
